cli/__init__.py
cli/main.py
cli/commands/__init__.py
cli/commands/create.py
cli/commands/delete.py
cli/commands/login.py
cli/commands/logout.py
cli/commands/read.py
cli/commands/update.py
cli/commands/whoami.py
server/__init__.py
server/app.py
server/auth.py
server/database.py
notescli_tool-1.0.0.dist-info/METADATA
notescli_tool-1.0.0.dist-info/WHEEL
notescli_tool-1.0.0.dist-info/entry_points.txt
notescli_tool-1.0.0.dist-info/top_level.txt
notescli_tool-1.0.0.dist-info/RECORD
